recgame/__init__.py
recgame/_min_dependencies.py
recgame/_version.py
recgame/environments/__init__.py
recgame/environments/base.py
recgame/environments/environments.py
recgame/populations/__init__.py
recgame/populations/action_set.py
recgame/populations/base.py
recgame/recourse/__init__.py
recgame/recourse/base.py
recgame/recourse/n_feature_recourse.py
recgame/recourse/actionable_recourse/__init__.py
recgame/recourse/actionable_recourse/actionable_recourse.py
recgame/recourse/actionable_recourse/builder.py
recgame/recourse/actionable_recourse/cplex_helper.py
recgame/recourse/actionable_recourse/flipset.py
recgame/recourse/actionable_recourse/utils.py
recgame/utils/__init__.py
recgame/utils/_data.py
recgame/visualization/__init__.py
recgame/visualization/plot_environment.py
recgame/visualization/simulations.py
recgame/visualization/swarmplot.py
recourse_game-0.1a1.dist-info/LICENSE
recourse_game-0.1a1.dist-info/METADATA
recourse_game-0.1a1.dist-info/WHEEL
recourse_game-0.1a1.dist-info/top_level.txt
recourse_game-0.1a1.dist-info/RECORD
