Metadata-Version: 2.1
Name: recourse-game
Version: 0.1a1
Summary: Implementation of the Multi Agent Dynamic Counterfactual Recourse framework.
Home-page: https://github.com/joaopfonseca/recourse-game
Download-URL: https://github.com/joaopfonseca/recourse-game
Maintainer: J. Fonseca
Maintainer-email: jpfonseca@novaims.unl.pt
License: MIT
Classifier: Intended Audience :: Science/Research
Classifier: Intended Audience :: Developers
Classifier: License :: OSI Approved
Classifier: Programming Language :: Python
Classifier: Topic :: Software Development
Classifier: Topic :: Scientific/Engineering
Classifier: Operating System :: Microsoft :: Windows
Classifier: Operating System :: POSIX
Classifier: Operating System :: Unix
Classifier: Operating System :: MacOS
Classifier: Programming Language :: Python :: 3.8
Classifier: Programming Language :: Python :: 3.9
Classifier: Programming Language :: Python :: 3.10
Classifier: Programming Language :: Python :: 3.11
License-File: LICENSE
Requires-Dist: pandas (>=1.3.5)
Requires-Dist: numpy (>=1.14.6)
Requires-Dist: scikit-learn (>=1.0.0)
Requires-Dist: ml-research (>=0.4.1)
Requires-Dist: matplotlib (>=2.2.3)
Requires-Dist: cplex (>=22.1.0.0)
Requires-Dist: prettytable (>=3.6.0)
Provides-Extra: all
Requires-Dist: pandas (>=1.3.5) ; extra == 'all'
Requires-Dist: numpy (>=1.14.6) ; extra == 'all'
Requires-Dist: scikit-learn (>=1.0.0) ; extra == 'all'
Requires-Dist: ml-research (>=0.4.1) ; extra == 'all'
Requires-Dist: matplotlib (>=2.2.3) ; extra == 'all'
Requires-Dist: cplex (>=22.1.0.0) ; extra == 'all'
Requires-Dist: prettytable (>=3.6.0) ; extra == 'all'
Requires-Dist: flake8 (>=3.8.2) ; extra == 'all'
Requires-Dist: black (>=22.3) ; extra == 'all'
Requires-Dist: pylint (>=2.12.2) ; extra == 'all'
Provides-Extra: docs
Provides-Extra: examples
Provides-Extra: optional
Provides-Extra: tests
Requires-Dist: flake8 (>=3.8.2) ; extra == 'tests'
Requires-Dist: black (>=22.3) ; extra == 'tests'
Requires-Dist: pylint (>=2.12.2) ; extra == 'tests'
